{
  "parent": "minecraft:recipes/root",
  "criteria": {
    "has_mithril_shovel": {
      "conditions": {
        "items": [
          {
            "items": "muckcraftmod:mithril_shovel"
          }
        ]
      },
      "trigger": "minecraft:inventory_changed"
    },
    "has_the_recipe": {
      "conditions": {
        "recipe": "muckcraftmod:mithril_shovel"
      },
      "trigger": "minecraft:recipe_unlocked"
    }
  },
  "requirements": [
    [
      "has_the_recipe",
      "has_mithril_shovel"
    ]
  ],
  "rewards": {
    "recipes": [
      "muckcraftmod:mithril_shovel"
    ]
  }
}