{
  "criteria": {
    "obamium": {
      "conditions": {
        "items": [
          {
            "items": "muckcraftmod:obamium_ingot"
          }
        ]
      },
      "trigger": "minecraft:inventory_changed"
    }
  },
  "display": {
    "description": {
      "translate": "advancements.muckcraftmod.smelt_obamium.description"
    },
    "icon": {
      "count": 1,
      "id": "muckcraftmod:obamium_ingot"
    },
    "title": {
      "translate": "advancements.muckcraftmod.smelt_obamium.title"
    },
    "background": "muckcraftmod:textures/block/raw_obamium_block.png",
    "background": "muckcraftmod:textures/gui/advancements/backgrounds/raw_obamium_block.png"
  },
  "requirements": [
    [
      "obamium"
    ]
  ],
  "sends_telemetry_event": true
}